{
  "id": "166",
  "url": "https://www.csszengarden.com/166",
  "css_url": "https://www.csszengarden.com/166/166.css",
  "description": "This design showcases a minimalist aesthetic with a dark background, creating a contemporary and sophisticated feel. The use of boxes with rounded corners provides a modern twist, while the contrasting colors and textures add depth. The typography is clean and straightforward, with strategically placed headers to guide the viewer's attention across the layout. Imagery of nature complements the theme, adding a touch of organic elegance.",
  "categories": [
    "Minimalism",
    "Modern",
    "Sophistication",
    "Nature",
    "Typography"
  ],
  "visual_characteristics": [
    "Dark Background",
    "Contrasting Colors",
    "Rounded Corners",
    "Clean Typography",
    "Textured Elements"
  ]
}