{
  "id": "186",
  "url": "https://www.csszengarden.com/186",
  "css_url": "https://www.csszengarden.com/186/186.css",
  "description": "The design features a fresh and calming aesthetic, with a predominant use of soft pastel green and pink hues, enhanced by floral imagery that exudes a natural and serene atmosphere. The typography is clean and well-organized, enabling easy readability, while a sidebar with navigation links provides clear structure and accessibility.",
  "categories": [
    "web page layout",
    "clean design",
    "readability",
    "navigation"
  ],
  "visual_characteristics": [
    "pastel color scheme",
    "floral imagery",
    "sans-serif typography",
    "structured layout"
  ]
}